flask_rest_orm/__init__.py
flask_rest_orm/api.py
flask_rest_orm/conftest.py
flask_rest_orm/resources/__init__.py
flask_rest_orm/resources/docgeneration.py
flask_rest_orm/resources/resources.py
flask_rest_orm/resources/utils.py
flask_rest_orm/serialization/__init__.py
flask_rest_orm/serialization/modelserializer.py
flask_rest_orm/serialization/serializer.py
flask_rest_orm-0.5.0.data/data/LICENSE
flask_rest_orm-0.5.0.dist-info/DESCRIPTION.rst
flask_rest_orm-0.5.0.dist-info/METADATA
flask_rest_orm-0.5.0.dist-info/RECORD
flask_rest_orm-0.5.0.dist-info/WHEEL
flask_rest_orm-0.5.0.dist-info/metadata.json
flask_rest_orm-0.5.0.dist-info/top_level.txt
