Metadata-Version: 2.0
Name: flask-rest-orm
Version: 0.5.0
Summary: Flask extension to build REST APIs based on SQLAlchemy models 
Home-page: https://github.com/ESSS/flask-rest-orm
Author: ESSS Ltda
Author-email: igor@esss.com.br
License: MIT
Keywords: flask sqlalchemy orm
Platform: UNKNOWN
Classifier: Development Status :: 3 - Alpha
Classifier: Intended Audience :: Developers
Classifier: License :: OSI Approved :: MIT License
Classifier: Operating System :: OS Independent
Classifier: Programming Language :: Python :: 3.4
Classifier: Programming Language :: Python :: 3.5
Classifier: Programming Language :: Python :: 3.6
Classifier: Topic :: Database :: Front-Ends
Classifier: Topic :: Internet :: WWW/HTTP
Requires-Python: >=3.4
Requires-Dist: flask-restful (>=0.3.0)
Requires-Dist: flask-sqlalchemy (>=2.3.0)
